Metadata-Version: 2.1
Name: firstimpressionbeta
Version: 1.0.19
Summary: First Python library
Home-page: UNKNOWN
Author: FirstImpression
Author-email: programming@firstimpression.nl
License: MIT
Platform: UNKNOWN
Classifier: Development Status :: 3 - Alpha
Classifier: Intended Audience :: Developers
Classifier: Topic :: Software Development :: Build Tools
Classifier: License :: OSI Approved :: MIT License
Classifier: Programming Language :: Python :: 3.6
Classifier: Programming Language :: Python :: 2.7
Requires-Dist: requests
Requires-Dist: geopy
Requires-Dist: wheel
Requires-Dist: beautifulsoup4
Requires-Dist: lxml
Requires-Dist: pytz
